{
  "clones": [
    {
      "timestamp": "2026-03-14T00:00:00Z",
      "count": 3,
      "uniques": 3
    },
    {
      "timestamp": "2026-03-15T00:00:00Z",
      "count": 2,
      "uniques": 2
    },
    {
      "timestamp": "2026-03-16T00:00:00Z",
      "count": 1,
      "uniques": 1
    },
    {
      "timestamp": "2026-03-17T00:00:00Z",
      "count": 1,
      "uniques": 1
    },
    {
      "timestamp": "2026-03-18T00:00:00Z",
      "count": 1,
      "uniques": 1
    },
    {
      "timestamp": "2026-03-19T00:00:00Z",
      "count": 1,
      "uniques": 1
    },
    {
      "timestamp": "2026-03-20T00:00:00Z",
      "count": 2,
      "uniques": 2
    },
    {
      "timestamp": "2026-03-21T00:00:00Z",
      "count": 2,
      "uniques": 2
    },
    {
      "timestamp": "2026-03-22T00:00:00Z",
      "count": 2,
      "uniques": 2
    },
    {
      "timestamp": "2026-03-23T00:00:00Z",
      "count": 2,
      "uniques": 2
    },
    {
      "timestamp": "2026-03-24T00:00:00Z",
      "count": 1,
      "uniques": 1
    },
    {
      "timestamp": "2026-03-25T00:00:00Z",
      "count": 1,
      "uniques": 1
    },
    {
      "timestamp": "2026-03-26T00:00:00Z",
      "count": 1,
      "uniques": 1
    },
    {
      "timestamp": "2026-03-27T00:00:00Z",
      "count": 1,
      "uniques": 1
    },
    {
      "timestamp": "2026-03-28T00:00:00Z",
      "count": 21,
      "uniques": 13
    },
    {
      "timestamp": "2026-03-29T00:00:00Z",
      "count": 9,
      "uniques": 9
    },
    {
      "timestamp": "2026-03-30T00:00:00Z",
      "count": 6,
      "uniques": 5
    },
    {
      "timestamp": "2026-03-31T00:00:00Z",
      "count": 17,
      "uniques": 10
    },
    {
      "timestamp": "2026-04-01T00:00:00Z",
      "count": 11,
      "uniques": 6
    },
    {
      "timestamp": "2026-04-02T00:00:00Z",
      "count": 12,
      "uniques": 6
    },
    {
      "timestamp": "2026-04-03T00:00:00Z",
      "count": 10,
      "uniques": 5
    },
    {
      "timestamp": "2026-04-04T00:00:00Z",
      "count": 9,
      "uniques": 8
    },
    {
      "timestamp": "2026-04-05T00:00:00Z",
      "count": 8,
      "uniques": 7
    },
    {
      "timestamp": "2026-04-06T00:00:00Z",
      "count": 9,
      "uniques": 6
    },
    {
      "timestamp": "2026-04-07T00:00:00Z",
      "count": 16,
      "uniques": 9
    },
    {
      "timestamp": "2026-04-08T00:00:00Z",
      "count": 20,
      "uniques": 10
    },
    {
      "timestamp": "2026-04-09T00:00:00Z",
      "count": 20,
      "uniques": 11
    },
    {
      "timestamp": "2026-04-10T00:00:00Z",
      "count": 25,
      "uniques": 12
    },
    {
      "timestamp": "2026-04-11T00:00:00Z",
      "count": 26,
      "uniques": 13
    },
    {
      "timestamp": "2026-04-12T00:00:00Z",
      "count": 11,
      "uniques": 6
    },
    {
      "timestamp": "2026-04-13T00:00:00Z",
      "count": 24,
      "uniques": 13
    },
    {
      "timestamp": "2026-04-14T00:00:00Z",
      "count": 26,
      "uniques": 13
    },
    {
      "timestamp": "2026-04-15T00:00:00Z",
      "count": 11,
      "uniques": 5
    },
    {
      "timestamp": "2026-04-16T00:00:00Z",
      "count": 10,
      "uniques": 5
    },
    {
      "timestamp": "2026-04-17T00:00:00Z",
      "count": 17,
      "uniques": 8
    },
    {
      "timestamp": "2026-04-18T00:00:00Z",
      "count": 25,
      "uniques": 13
    },
    {
      "timestamp": "2026-04-19T00:00:00Z",
      "count": 14,
      "uniques": 8
    },
    {
      "timestamp": "2026-04-20T00:00:00Z",
      "count": 12,
      "uniques": 6
    },
    {
      "timestamp": "2026-04-21T00:00:00Z",
      "count": 21,
      "uniques": 10
    },
    {
      "timestamp": "2026-04-22T00:00:00Z",
      "count": 22,
      "uniques": 8
    },
    {
      "timestamp": "2026-04-23T00:00:00Z",
      "count": 56,
      "uniques": 17
    },
    {
      "timestamp": "2026-04-24T00:00:00Z",
      "count": 31,
      "uniques": 13
    }
  ],
  "views": [
    {
      "timestamp": "2026-03-14T00:00:00Z",
      "count": 0,
      "uniques": 0
    },
    {
      "timestamp": "2026-03-15T00:00:00Z",
      "count": 0,
      "uniques": 0
    },
    {
      "timestamp": "2026-03-16T00:00:00Z",
      "count": 1,
      "uniques": 1
    },
    {
      "timestamp": "2026-03-17T00:00:00Z",
      "count": 1,
      "uniques": 1
    },
    {
      "timestamp": "2026-03-18T00:00:00Z",
      "count": 3,
      "uniques": 2
    },
    {
      "timestamp": "2026-03-19T00:00:00Z",
      "count": 1,
      "uniques": 1
    },
    {
      "timestamp": "2026-03-20T00:00:00Z",
      "count": 0,
      "uniques": 0
    },
    {
      "timestamp": "2026-03-21T00:00:00Z",
      "count": 0,
      "uniques": 0
    },
    {
      "timestamp": "2026-03-22T00:00:00Z",
      "count": 0,
      "uniques": 0
    },
    {
      "timestamp": "2026-03-23T00:00:00Z",
      "count": 0,
      "uniques": 0
    },
    {
      "timestamp": "2026-03-24T00:00:00Z",
      "count": 1,
      "uniques": 1
    },
    {
      "timestamp": "2026-03-25T00:00:00Z",
      "count": 2,
      "uniques": 1
    },
    {
      "timestamp": "2026-03-26T00:00:00Z",
      "count": 0,
      "uniques": 0
    },
    {
      "timestamp": "2026-03-27T00:00:00Z",
      "count": 0,
      "uniques": 0
    },
    {
      "timestamp": "2026-03-28T00:00:00Z",
      "count": 3,
      "uniques": 1
    },
    {
      "timestamp": "2026-03-29T00:00:00Z",
      "count": 0,
      "uniques": 0
    },
    {
      "timestamp": "2026-03-30T00:00:00Z",
      "count": 0,
      "uniques": 0
    },
    {
      "timestamp": "2026-03-31T00:00:00Z",
      "count": 0,
      "uniques": 0
    },
    {
      "timestamp": "2026-04-01T00:00:00Z",
      "count": 0,
      "uniques": 0
    },
    {
      "timestamp": "2026-04-02T00:00:00Z",
      "count": 5,
      "uniques": 3
    },
    {
      "timestamp": "2026-04-03T00:00:00Z",
      "count": 0,
      "uniques": 0
    },
    {
      "timestamp": "2026-04-04T00:00:00Z",
      "count": 0,
      "uniques": 0
    },
    {
      "timestamp": "2026-04-05T00:00:00Z",
      "count": 0,
      "uniques": 0
    },
    {
      "timestamp": "2026-04-06T00:00:00Z",
      "count": 0,
      "uniques": 0
    },
    {
      "timestamp": "2026-04-07T00:00:00Z",
      "count": 4,
      "uniques": 1
    },
    {
      "timestamp": "2026-04-08T00:00:00Z",
      "count": 2,
      "uniques": 1
    },
    {
      "timestamp": "2026-04-09T00:00:00Z",
      "count": 1,
      "uniques": 1
    },
    {
      "timestamp": "2026-04-10T00:00:00Z",
      "count": 0,
      "uniques": 0
    },
    {
      "timestamp": "2026-04-11T00:00:00Z",
      "count": 0,
      "uniques": 0
    },
    {
      "timestamp": "2026-04-12T00:00:00Z",
      "count": 0,
      "uniques": 0
    },
    {
      "timestamp": "2026-04-13T00:00:00Z",
      "count": 0,
      "uniques": 0
    },
    {
      "timestamp": "2026-04-14T00:00:00Z",
      "count": 0,
      "uniques": 0
    },
    {
      "timestamp": "2026-04-15T00:00:00Z",
      "count": 0,
      "uniques": 0
    },
    {
      "timestamp": "2026-04-16T00:00:00Z",
      "count": 0,
      "uniques": 0
    },
    {
      "timestamp": "2026-04-17T00:00:00Z",
      "count": 0,
      "uniques": 0
    },
    {
      "timestamp": "2026-04-18T00:00:00Z",
      "count": 0,
      "uniques": 0
    },
    {
      "timestamp": "2026-04-19T00:00:00Z",
      "count": 0,
      "uniques": 0
    },
    {
      "timestamp": "2026-04-20T00:00:00Z",
      "count": 0,
      "uniques": 0
    },
    {
      "timestamp": "2026-04-21T00:00:00Z",
      "count": 0,
      "uniques": 0
    },
    {
      "timestamp": "2026-04-22T00:00:00Z",
      "count": 0,
      "uniques": 0
    },
    {
      "timestamp": "2026-04-23T00:00:00Z",
      "count": 1,
      "uniques": 1
    },
    {
      "timestamp": "2026-04-24T00:00:00Z",
      "count": 3,
      "uniques": 1
    }
  ],
  "referrers": [
    {
      "date": "2026-03-28",
      "sources": [
        {
          "referrer": "github.com",
          "count": 2,
          "uniques": 1
        }
      ]
    },
    {
      "date": "2026-03-29",
      "sources": [
        {
          "referrer": "github.com",
          "count": 2,
          "uniques": 1
        }
      ]
    },
    {
      "date": "2026-03-30",
      "sources": [
        {
          "referrer": "github.com",
          "count": 2,
          "uniques": 1
        }
      ]
    },
    {
      "date": "2026-03-31",
      "sources": [
        {
          "referrer": "github.com",
          "count": 2,
          "uniques": 1
        }
      ]
    },
    {
      "date": "2026-04-01",
      "sources": [
        {
          "referrer": "github.com",
          "count": 1,
          "uniques": 1
        }
      ]
    },
    {
      "date": "2026-04-02",
      "sources": [
        {
          "referrer": "github.com",
          "count": 1,
          "uniques": 1
        }
      ]
    },
    {
      "date": "2026-04-03",
      "sources": [
        {
          "referrer": "github.com",
          "count": 1,
          "uniques": 1
        }
      ]
    },
    {
      "date": "2026-04-04",
      "sources": [
        {
          "referrer": "github.com",
          "count": 4,
          "uniques": 2
        },
        {
          "referrer": "reddit.com",
          "count": 1,
          "uniques": 1
        }
      ]
    },
    {
      "date": "2026-04-05",
      "sources": [
        {
          "referrer": "github.com",
          "count": 4,
          "uniques": 2
        },
        {
          "referrer": "reddit.com",
          "count": 1,
          "uniques": 1
        }
      ]
    },
    {
      "date": "2026-04-06",
      "sources": [
        {
          "referrer": "github.com",
          "count": 4,
          "uniques": 2
        },
        {
          "referrer": "reddit.com",
          "count": 1,
          "uniques": 1
        }
      ]
    },
    {
      "date": "2026-04-07",
      "sources": [
        {
          "referrer": "github.com",
          "count": 4,
          "uniques": 2
        },
        {
          "referrer": "reddit.com",
          "count": 1,
          "uniques": 1
        }
      ]
    },
    {
      "date": "2026-04-08",
      "sources": [
        {
          "referrer": "github.com",
          "count": 5,
          "uniques": 3
        },
        {
          "referrer": "reddit.com",
          "count": 4,
          "uniques": 2
        }
      ]
    },
    {
      "date": "2026-04-09",
      "sources": [
        {
          "referrer": "github.com",
          "count": 5,
          "uniques": 3
        },
        {
          "referrer": "reddit.com",
          "count": 4,
          "uniques": 2
        }
      ]
    },
    {
      "date": "2026-04-10",
      "sources": [
        {
          "referrer": "github.com",
          "count": 5,
          "uniques": 3
        },
        {
          "referrer": "reddit.com",
          "count": 5,
          "uniques": 3
        }
      ]
    },
    {
      "date": "2026-04-11",
      "sources": [
        {
          "referrer": "github.com",
          "count": 5,
          "uniques": 3
        },
        {
          "referrer": "reddit.com",
          "count": 5,
          "uniques": 3
        }
      ]
    },
    {
      "date": "2026-04-12",
      "sources": [
        {
          "referrer": "github.com",
          "count": 5,
          "uniques": 3
        },
        {
          "referrer": "reddit.com",
          "count": 5,
          "uniques": 3
        }
      ]
    },
    {
      "date": "2026-04-13",
      "sources": [
        {
          "referrer": "github.com",
          "count": 5,
          "uniques": 3
        },
        {
          "referrer": "reddit.com",
          "count": 5,
          "uniques": 3
        }
      ]
    },
    {
      "date": "2026-04-14",
      "sources": [
        {
          "referrer": "github.com",
          "count": 5,
          "uniques": 3
        },
        {
          "referrer": "reddit.com",
          "count": 5,
          "uniques": 3
        }
      ]
    },
    {
      "date": "2026-04-15",
      "sources": [
        {
          "referrer": "github.com",
          "count": 5,
          "uniques": 3
        },
        {
          "referrer": "reddit.com",
          "count": 5,
          "uniques": 3
        }
      ]
    },
    {
      "date": "2026-04-16",
      "sources": [
        {
          "referrer": "github.com",
          "count": 5,
          "uniques": 3
        },
        {
          "referrer": "reddit.com",
          "count": 5,
          "uniques": 3
        }
      ]
    },
    {
      "date": "2026-04-17",
      "sources": [
        {
          "referrer": "github.com",
          "count": 5,
          "uniques": 3
        },
        {
          "referrer": "reddit.com",
          "count": 5,
          "uniques": 3
        }
      ]
    },
    {
      "date": "2026-04-18",
      "sources": [
        {
          "referrer": "reddit.com",
          "count": 4,
          "uniques": 2
        },
        {
          "referrer": "github.com",
          "count": 2,
          "uniques": 2
        }
      ]
    },
    {
      "date": "2026-04-19",
      "sources": [
        {
          "referrer": "reddit.com",
          "count": 4,
          "uniques": 2
        },
        {
          "referrer": "github.com",
          "count": 2,
          "uniques": 2
        }
      ]
    },
    {
      "date": "2026-04-20",
      "sources": [
        {
          "referrer": "reddit.com",
          "count": 4,
          "uniques": 2
        },
        {
          "referrer": "github.com",
          "count": 2,
          "uniques": 2
        }
      ]
    },
    {
      "date": "2026-04-21",
      "sources": [
        {
          "referrer": "reddit.com",
          "count": 4,
          "uniques": 2
        },
        {
          "referrer": "github.com",
          "count": 2,
          "uniques": 2
        }
      ]
    },
    {
      "date": "2026-04-22",
      "sources": [
        {
          "referrer": "github.com",
          "count": 1,
          "uniques": 1
        },
        {
          "referrer": "reddit.com",
          "count": 1,
          "uniques": 1
        }
      ]
    },
    {
      "date": "2026-04-23",
      "sources": [
        {
          "referrer": "github.com",
          "count": 1,
          "uniques": 1
        },
        {
          "referrer": "reddit.com",
          "count": 1,
          "uniques": 1
        }
      ]
    },
    {
      "date": "2026-04-24",
      "sources": [
        {
          "referrer": "github.com",
          "count": 1,
          "uniques": 1
        }
      ]
    },
    {
      "date": "2026-04-25",
      "sources": [
        {
          "referrer": "github.com",
          "count": 1,
          "uniques": 1
        }
      ]
    },
    {
      "date": "2026-04-26",
      "sources": [
        {
          "referrer": "Google",
          "count": 3,
          "uniques": 1
        },
        {
          "referrer": "github.com",
          "count": 1,
          "uniques": 1
        }
      ]
    }
  ],
  "paths": [
    {
      "date": "2026-03-28",
      "pages": [
        {
          "path": "/NYBaywatch/AgrusScanner",
          "title": "NYBaywatch/AgrusScanner",
          "count": 4,
          "uniques": 3
        },
        {
          "path": "/NYBaywatch/AgrusScanner/releases",
          "title": "Releases · NYBaywatch/AgrusScanner",
          "count": 2,
          "uniques": 1
        },
        {
          "path": "/NYBaywatch/AgrusScanner/tags",
          "title": "Tags · NYBaywatch/AgrusScanner",
          "count": 1,
          "uniques": 1
        },
        {
          "path": "/NYBaywatch/AgrusScanner/tree/master/infra/agrus-update-lambda",
          "title": "AgrusScanner/infra/agrus-update-lambda at master · NYBaywatch/AgrusScanner · ...",
          "count": 1,
          "uniques": 1
        },
        {
          "path": "/nybaywatch/agrusscanner",
          "title": "GitHub - NYBaywatch/AgrusScanner · GitHub",
          "count": 1,
          "uniques": 1
        }
      ]
    },
    {
      "date": "2026-03-29",
      "pages": [
        {
          "path": "/NYBaywatch/AgrusScanner",
          "title": "NYBaywatch/AgrusScanner",
          "count": 4,
          "uniques": 3
        },
        {
          "path": "/NYBaywatch/AgrusScanner/releases",
          "title": "Releases · NYBaywatch/AgrusScanner",
          "count": 2,
          "uniques": 1
        },
        {
          "path": "/NYBaywatch/AgrusScanner/tags",
          "title": "Tags · NYBaywatch/AgrusScanner",
          "count": 1,
          "uniques": 1
        },
        {
          "path": "/NYBaywatch/AgrusScanner/tree/master/infra/agrus-update-lambda",
          "title": "AgrusScanner/infra/agrus-update-lambda at master · NYBaywatch/AgrusScanner · ...",
          "count": 1,
          "uniques": 1
        },
        {
          "path": "/nybaywatch/agrusscanner",
          "title": "GitHub - NYBaywatch/AgrusScanner · GitHub",
          "count": 1,
          "uniques": 1
        }
      ]
    },
    {
      "date": "2026-03-30",
      "pages": [
        {
          "path": "/NYBaywatch/AgrusScanner",
          "title": "NYBaywatch/AgrusScanner",
          "count": 4,
          "uniques": 3
        },
        {
          "path": "/NYBaywatch/AgrusScanner/actions/runs/23679359724",
          "title": "Persist GitHub Traffic Stats · NYBaywatch/AgrusScanner@8cb6a4a",
          "count": 2,
          "uniques": 1
        },
        {
          "path": "/NYBaywatch/AgrusScanner/releases",
          "title": "Releases · NYBaywatch/AgrusScanner",
          "count": 2,
          "uniques": 1
        },
        {
          "path": "/NYBaywatch/AgrusScanner/actions/runs/23679359724/job/68988563287",
          "title": "Persist GitHub Traffic Stats · NYBaywatch/AgrusScanner@8cb6a4a",
          "count": 1,
          "uniques": 1
        },
        {
          "path": "/NYBaywatch/AgrusScanner/tags",
          "title": "Tags · NYBaywatch/AgrusScanner",
          "count": 1,
          "uniques": 1
        },
        {
          "path": "/NYBaywatch/AgrusScanner/tree/master/infra/agrus-update-lambda",
          "title": "AgrusScanner/infra/agrus-update-lambda at master · NYBaywatch/AgrusScanner · ...",
          "count": 1,
          "uniques": 1
        },
        {
          "path": "/nybaywatch/agrusscanner",
          "title": "GitHub - NYBaywatch/AgrusScanner · GitHub",
          "count": 1,
          "uniques": 1
        }
      ]
    },
    {
      "date": "2026-03-31",
      "pages": [
        {
          "path": "/NYBaywatch/AgrusScanner",
          "title": "NYBaywatch/AgrusScanner",
          "count": 4,
          "uniques": 3
        },
        {
          "path": "/NYBaywatch/AgrusScanner/actions/runs/23679359724",
          "title": "Persist GitHub Traffic Stats · NYBaywatch/AgrusScanner@8cb6a4a",
          "count": 2,
          "uniques": 1
        },
        {
          "path": "/NYBaywatch/AgrusScanner/releases",
          "title": "Releases · NYBaywatch/AgrusScanner",
          "count": 2,
          "uniques": 1
        },
        {
          "path": "/NYBaywatch/AgrusScanner/actions/runs/23679359724/job/68988563287",
          "title": "Persist GitHub Traffic Stats · NYBaywatch/AgrusScanner@8cb6a4a",
          "count": 1,
          "uniques": 1
        },
        {
          "path": "/NYBaywatch/AgrusScanner/tags",
          "title": "Tags · NYBaywatch/AgrusScanner",
          "count": 1,
          "uniques": 1
        },
        {
          "path": "/NYBaywatch/AgrusScanner/tree/master/infra/agrus-update-lambda",
          "title": "AgrusScanner/infra/agrus-update-lambda at master · NYBaywatch/AgrusScanner · ...",
          "count": 1,
          "uniques": 1
        },
        {
          "path": "/nybaywatch/agrusscanner",
          "title": "GitHub - NYBaywatch/AgrusScanner · GitHub",
          "count": 1,
          "uniques": 1
        }
      ]
    },
    {
      "date": "2026-04-01",
      "pages": [
        {
          "path": "/NYBaywatch/AgrusScanner",
          "title": "NYBaywatch/AgrusScanner",
          "count": 3,
          "uniques": 3
        },
        {
          "path": "/NYBaywatch/AgrusScanner/actions/runs/23679359724",
          "title": "Persist GitHub Traffic Stats · NYBaywatch/AgrusScanner@8cb6a4a",
          "count": 2,
          "uniques": 1
        },
        {
          "path": "/NYBaywatch/AgrusScanner/releases",
          "title": "Releases · NYBaywatch/AgrusScanner",
          "count": 2,
          "uniques": 1
        },
        {
          "path": "/NYBaywatch/AgrusScanner/actions/runs/23679359724/job/68988563287",
          "title": "Persist GitHub Traffic Stats · NYBaywatch/AgrusScanner@8cb6a4a",
          "count": 1,
          "uniques": 1
        },
        {
          "path": "/NYBaywatch/AgrusScanner/tags",
          "title": "Tags · NYBaywatch/AgrusScanner",
          "count": 1,
          "uniques": 1
        },
        {
          "path": "/NYBaywatch/AgrusScanner/tree/master/infra/agrus-update-lambda",
          "title": "AgrusScanner/infra/agrus-update-lambda at master · NYBaywatch/AgrusScanner · ...",
          "count": 1,
          "uniques": 1
        }
      ]
    },
    {
      "date": "2026-04-02",
      "pages": [
        {
          "path": "/NYBaywatch/AgrusScanner",
          "title": "Overview",
          "count": 2,
          "uniques": 2
        },
        {
          "path": "/NYBaywatch/AgrusScanner/actions/runs/23679359724",
          "title": "/actions/runs/23679359724",
          "count": 2,
          "uniques": 1
        },
        {
          "path": "/NYBaywatch/AgrusScanner/actions/runs/23679359724/job/68988563287",
          "title": "/actions/runs/23679359724/job/68988563287",
          "count": 1,
          "uniques": 1
        },
        {
          "path": "/NYBaywatch/AgrusScanner/tags",
          "title": "/tags",
          "count": 1,
          "uniques": 1
        },
        {
          "path": "/NYBaywatch/AgrusScanner/tree/master/infra/agrus-update-lambda",
          "title": "/tree/master/infra/agrus-update-lambda",
          "count": 1,
          "uniques": 1
        }
      ]
    },
    {
      "date": "2026-04-03",
      "pages": [
        {
          "path": "/NYBaywatch/AgrusScanner",
          "title": "Overview",
          "count": 2,
          "uniques": 2
        },
        {
          "path": "/NYBaywatch/AgrusScanner/actions/runs/23679359724",
          "title": "/actions/runs/23679359724",
          "count": 2,
          "uniques": 1
        },
        {
          "path": "/NYBaywatch/AgrusScanner/actions/runs/23679359724/job/68988563287",
          "title": "/actions/runs/23679359724/job/68988563287",
          "count": 1,
          "uniques": 1
        },
        {
          "path": "/NYBaywatch/AgrusScanner/tags",
          "title": "/tags",
          "count": 1,
          "uniques": 1
        },
        {
          "path": "/NYBaywatch/AgrusScanner/tree/master/infra/agrus-update-lambda",
          "title": "/tree/master/infra/agrus-update-lambda",
          "count": 1,
          "uniques": 1
        }
      ]
    },
    {
      "date": "2026-04-04",
      "pages": [
        {
          "path": "/NYBaywatch/AgrusScanner",
          "title": "Overview",
          "count": 6,
          "uniques": 4
        },
        {
          "path": "/NYBaywatch/AgrusScanner/actions/runs/23679359724",
          "title": "/actions/runs/23679359724",
          "count": 2,
          "uniques": 1
        },
        {
          "path": "/NYBaywatch/AgrusScanner/actions/runs/23679359724/job/68988563287",
          "title": "/actions/runs/23679359724/job/68988563287",
          "count": 1,
          "uniques": 1
        },
        {
          "path": "/NYBaywatch/AgrusScanner/fork",
          "title": "/fork",
          "count": 1,
          "uniques": 1
        },
        {
          "path": "/NYBaywatch/AgrusScanner/tags",
          "title": "/tags",
          "count": 1,
          "uniques": 1
        }
      ]
    },
    {
      "date": "2026-04-05",
      "pages": [
        {
          "path": "/NYBaywatch/AgrusScanner",
          "title": "Overview",
          "count": 6,
          "uniques": 4
        },
        {
          "path": "/NYBaywatch/AgrusScanner/actions/runs/23679359724",
          "title": "/actions/runs/23679359724",
          "count": 2,
          "uniques": 1
        },
        {
          "path": "/NYBaywatch/AgrusScanner/actions/runs/23679359724/job/68988563287",
          "title": "/actions/runs/23679359724/job/68988563287",
          "count": 1,
          "uniques": 1
        },
        {
          "path": "/NYBaywatch/AgrusScanner/fork",
          "title": "/fork",
          "count": 1,
          "uniques": 1
        },
        {
          "path": "/NYBaywatch/AgrusScanner/tags",
          "title": "/tags",
          "count": 1,
          "uniques": 1
        }
      ]
    },
    {
      "date": "2026-04-06",
      "pages": [
        {
          "path": "/NYBaywatch/AgrusScanner",
          "title": "Overview",
          "count": 6,
          "uniques": 4
        },
        {
          "path": "/NYBaywatch/AgrusScanner/actions/runs/23679359724",
          "title": "/actions/runs/23679359724",
          "count": 2,
          "uniques": 1
        },
        {
          "path": "/NYBaywatch/AgrusScanner/actions/runs/23679359724/job/68988563287",
          "title": "/actions/runs/23679359724/job/68988563287",
          "count": 1,
          "uniques": 1
        },
        {
          "path": "/NYBaywatch/AgrusScanner/fork",
          "title": "/fork",
          "count": 1,
          "uniques": 1
        },
        {
          "path": "/NYBaywatch/AgrusScanner/tags",
          "title": "/tags",
          "count": 1,
          "uniques": 1
        }
      ]
    },
    {
      "date": "2026-04-07",
      "pages": [
        {
          "path": "/NYBaywatch/AgrusScanner",
          "title": "Overview",
          "count": 6,
          "uniques": 4
        },
        {
          "path": "/NYBaywatch/AgrusScanner/actions/runs/23679359724",
          "title": "/actions/runs/23679359724",
          "count": 2,
          "uniques": 1
        },
        {
          "path": "/NYBaywatch/AgrusScanner/actions/runs/23679359724/job/68988563287",
          "title": "/actions/runs/23679359724/job/68988563287",
          "count": 1,
          "uniques": 1
        },
        {
          "path": "/NYBaywatch/AgrusScanner/fork",
          "title": "/fork",
          "count": 1,
          "uniques": 1
        },
        {
          "path": "/NYBaywatch/AgrusScanner/tags",
          "title": "/tags",
          "count": 1,
          "uniques": 1
        }
      ]
    },
    {
      "date": "2026-04-08",
      "pages": [
        {
          "path": "/NYBaywatch/AgrusScanner",
          "title": "Overview",
          "count": 7,
          "uniques": 4
        },
        {
          "path": "/NYBaywatch/AgrusScanner/actions/runs/23679359724",
          "title": "/actions/runs/23679359724",
          "count": 2,
          "uniques": 1
        },
        {
          "path": "/NYBaywatch/AgrusScanner/actions/runs/23679359724/job/68988563287",
          "title": "/actions/runs/23679359724/job/68988563287",
          "count": 1,
          "uniques": 1
        },
        {
          "path": "/NYBaywatch/AgrusScanner/fork",
          "title": "/fork",
          "count": 1,
          "uniques": 1
        },
        {
          "path": "/NYBaywatch/AgrusScanner/issues",
          "title": "/issues",
          "count": 1,
          "uniques": 1
        },
        {
          "path": "/NYBaywatch/AgrusScanner/releases/tag/v0.2.2",
          "title": "/releases/tag/v0.2.2",
          "count": 1,
          "uniques": 1
        },
        {
          "path": "/NYBaywatch/AgrusScanner/tags",
          "title": "/tags",
          "count": 1,
          "uniques": 1
        }
      ]
    },
    {
      "date": "2026-04-09",
      "pages": [
        {
          "path": "/NYBaywatch/AgrusScanner",
          "title": "Overview",
          "count": 7,
          "uniques": 4
        },
        {
          "path": "/NYBaywatch/AgrusScanner/actions/runs/23679359724",
          "title": "/actions/runs/23679359724",
          "count": 2,
          "uniques": 1
        },
        {
          "path": "/NYBaywatch/AgrusScanner/actions/runs/23679359724/job/68988563287",
          "title": "/actions/runs/23679359724/job/68988563287",
          "count": 1,
          "uniques": 1
        },
        {
          "path": "/NYBaywatch/AgrusScanner/fork",
          "title": "/fork",
          "count": 1,
          "uniques": 1
        },
        {
          "path": "/NYBaywatch/AgrusScanner/issues",
          "title": "/issues",
          "count": 1,
          "uniques": 1
        },
        {
          "path": "/NYBaywatch/AgrusScanner/releases/tag/v0.2.2",
          "title": "/releases/tag/v0.2.2",
          "count": 1,
          "uniques": 1
        },
        {
          "path": "/NYBaywatch/AgrusScanner/tags",
          "title": "/tags",
          "count": 1,
          "uniques": 1
        }
      ]
    },
    {
      "date": "2026-04-10",
      "pages": [
        {
          "path": "/NYBaywatch/AgrusScanner",
          "title": "Overview",
          "count": 8,
          "uniques": 5
        },
        {
          "path": "/NYBaywatch/AgrusScanner/actions/runs/23679359724",
          "title": "/actions/runs/23679359724",
          "count": 2,
          "uniques": 1
        },
        {
          "path": "/NYBaywatch/AgrusScanner/actions/runs/23679359724/job/68988563287",
          "title": "/actions/runs/23679359724/job/68988563287",
          "count": 1,
          "uniques": 1
        },
        {
          "path": "/NYBaywatch/AgrusScanner/fork",
          "title": "/fork",
          "count": 1,
          "uniques": 1
        },
        {
          "path": "/NYBaywatch/AgrusScanner/issues",
          "title": "/issues",
          "count": 1,
          "uniques": 1
        },
        {
          "path": "/NYBaywatch/AgrusScanner/releases/tag/v0.2.2",
          "title": "/releases/tag/v0.2.2",
          "count": 1,
          "uniques": 1
        },
        {
          "path": "/NYBaywatch/agrusscanner",
          "title": "Overview",
          "count": 1,
          "uniques": 1
        }
      ]
    },
    {
      "date": "2026-04-11",
      "pages": [
        {
          "path": "/NYBaywatch/AgrusScanner",
          "title": "Overview",
          "count": 8,
          "uniques": 5
        },
        {
          "path": "/NYBaywatch/AgrusScanner/actions/runs/23679359724",
          "title": "/actions/runs/23679359724",
          "count": 2,
          "uniques": 1
        },
        {
          "path": "/NYBaywatch/AgrusScanner/actions/runs/23679359724/job/68988563287",
          "title": "/actions/runs/23679359724/job/68988563287",
          "count": 1,
          "uniques": 1
        },
        {
          "path": "/NYBaywatch/AgrusScanner/fork",
          "title": "/fork",
          "count": 1,
          "uniques": 1
        },
        {
          "path": "/NYBaywatch/AgrusScanner/issues",
          "title": "/issues",
          "count": 1,
          "uniques": 1
        },
        {
          "path": "/NYBaywatch/AgrusScanner/releases/tag/v0.2.2",
          "title": "/releases/tag/v0.2.2",
          "count": 1,
          "uniques": 1
        },
        {
          "path": "/NYBaywatch/agrusscanner",
          "title": "Overview",
          "count": 1,
          "uniques": 1
        }
      ]
    },
    {
      "date": "2026-04-12",
      "pages": [
        {
          "path": "/NYBaywatch/AgrusScanner",
          "title": "Overview",
          "count": 8,
          "uniques": 5
        },
        {
          "path": "/NYBaywatch/AgrusScanner/actions/runs/23679359724",
          "title": "/actions/runs/23679359724",
          "count": 2,
          "uniques": 1
        },
        {
          "path": "/NYBaywatch/AgrusScanner/actions/runs/23679359724/job/68988563287",
          "title": "/actions/runs/23679359724/job/68988563287",
          "count": 1,
          "uniques": 1
        },
        {
          "path": "/NYBaywatch/AgrusScanner/fork",
          "title": "/fork",
          "count": 1,
          "uniques": 1
        },
        {
          "path": "/NYBaywatch/AgrusScanner/issues",
          "title": "/issues",
          "count": 1,
          "uniques": 1
        },
        {
          "path": "/NYBaywatch/AgrusScanner/releases/tag/v0.2.2",
          "title": "/releases/tag/v0.2.2",
          "count": 1,
          "uniques": 1
        },
        {
          "path": "/NYBaywatch/agrusscanner",
          "title": "Overview",
          "count": 1,
          "uniques": 1
        }
      ]
    },
    {
      "date": "2026-04-13",
      "pages": [
        {
          "path": "/NYBaywatch/AgrusScanner",
          "title": "Overview",
          "count": 8,
          "uniques": 5
        },
        {
          "path": "/NYBaywatch/AgrusScanner/fork",
          "title": "/fork",
          "count": 1,
          "uniques": 1
        },
        {
          "path": "/NYBaywatch/AgrusScanner/issues",
          "title": "/issues",
          "count": 1,
          "uniques": 1
        },
        {
          "path": "/NYBaywatch/AgrusScanner/releases/tag/v0.2.2",
          "title": "/releases/tag/v0.2.2",
          "count": 1,
          "uniques": 1
        },
        {
          "path": "/NYBaywatch/agrusscanner",
          "title": "Overview",
          "count": 1,
          "uniques": 1
        }
      ]
    },
    {
      "date": "2026-04-14",
      "pages": [
        {
          "path": "/NYBaywatch/AgrusScanner",
          "title": "Overview",
          "count": 8,
          "uniques": 5
        },
        {
          "path": "/NYBaywatch/AgrusScanner/fork",
          "title": "/fork",
          "count": 1,
          "uniques": 1
        },
        {
          "path": "/NYBaywatch/AgrusScanner/issues",
          "title": "/issues",
          "count": 1,
          "uniques": 1
        },
        {
          "path": "/NYBaywatch/AgrusScanner/releases/tag/v0.2.2",
          "title": "/releases/tag/v0.2.2",
          "count": 1,
          "uniques": 1
        },
        {
          "path": "/NYBaywatch/agrusscanner",
          "title": "Overview",
          "count": 1,
          "uniques": 1
        }
      ]
    },
    {
      "date": "2026-04-15",
      "pages": [
        {
          "path": "/NYBaywatch/AgrusScanner",
          "title": "Overview",
          "count": 8,
          "uniques": 5
        },
        {
          "path": "/NYBaywatch/AgrusScanner/fork",
          "title": "/fork",
          "count": 1,
          "uniques": 1
        },
        {
          "path": "/NYBaywatch/AgrusScanner/issues",
          "title": "/issues",
          "count": 1,
          "uniques": 1
        },
        {
          "path": "/NYBaywatch/AgrusScanner/releases/tag/v0.2.2",
          "title": "/releases/tag/v0.2.2",
          "count": 1,
          "uniques": 1
        },
        {
          "path": "/NYBaywatch/agrusscanner",
          "title": "Overview",
          "count": 1,
          "uniques": 1
        }
      ]
    },
    {
      "date": "2026-04-16",
      "pages": [
        {
          "path": "/NYBaywatch/AgrusScanner",
          "title": "Overview",
          "count": 8,
          "uniques": 5
        },
        {
          "path": "/NYBaywatch/AgrusScanner/fork",
          "title": "/fork",
          "count": 1,
          "uniques": 1
        },
        {
          "path": "/NYBaywatch/AgrusScanner/issues",
          "title": "/issues",
          "count": 1,
          "uniques": 1
        },
        {
          "path": "/NYBaywatch/AgrusScanner/releases/tag/v0.2.2",
          "title": "/releases/tag/v0.2.2",
          "count": 1,
          "uniques": 1
        },
        {
          "path": "/NYBaywatch/agrusscanner",
          "title": "Overview",
          "count": 1,
          "uniques": 1
        }
      ]
    },
    {
      "date": "2026-04-17",
      "pages": [
        {
          "path": "/NYBaywatch/AgrusScanner",
          "title": "Overview",
          "count": 8,
          "uniques": 5
        },
        {
          "path": "/NYBaywatch/AgrusScanner/fork",
          "title": "/fork",
          "count": 1,
          "uniques": 1
        },
        {
          "path": "/NYBaywatch/AgrusScanner/issues",
          "title": "/issues",
          "count": 1,
          "uniques": 1
        },
        {
          "path": "/NYBaywatch/AgrusScanner/releases/tag/v0.2.2",
          "title": "/releases/tag/v0.2.2",
          "count": 1,
          "uniques": 1
        },
        {
          "path": "/NYBaywatch/agrusscanner",
          "title": "Overview",
          "count": 1,
          "uniques": 1
        }
      ]
    },
    {
      "date": "2026-04-18",
      "pages": [
        {
          "path": "/NYBaywatch/AgrusScanner",
          "title": "Overview",
          "count": 4,
          "uniques": 3
        },
        {
          "path": "/NYBaywatch/AgrusScanner/issues",
          "title": "/issues",
          "count": 1,
          "uniques": 1
        },
        {
          "path": "/NYBaywatch/AgrusScanner/releases/tag/v0.2.2",
          "title": "/releases/tag/v0.2.2",
          "count": 1,
          "uniques": 1
        },
        {
          "path": "/NYBaywatch/agrusscanner",
          "title": "Overview",
          "count": 1,
          "uniques": 1
        }
      ]
    },
    {
      "date": "2026-04-19",
      "pages": [
        {
          "path": "/NYBaywatch/AgrusScanner",
          "title": "Overview",
          "count": 4,
          "uniques": 3
        },
        {
          "path": "/NYBaywatch/AgrusScanner/issues",
          "title": "/issues",
          "count": 1,
          "uniques": 1
        },
        {
          "path": "/NYBaywatch/AgrusScanner/releases/tag/v0.2.2",
          "title": "/releases/tag/v0.2.2",
          "count": 1,
          "uniques": 1
        },
        {
          "path": "/NYBaywatch/agrusscanner",
          "title": "Overview",
          "count": 1,
          "uniques": 1
        }
      ]
    },
    {
      "date": "2026-04-20",
      "pages": [
        {
          "path": "/NYBaywatch/AgrusScanner",
          "title": "Overview",
          "count": 4,
          "uniques": 3
        },
        {
          "path": "/NYBaywatch/AgrusScanner/issues",
          "title": "/issues",
          "count": 1,
          "uniques": 1
        },
        {
          "path": "/NYBaywatch/AgrusScanner/releases/tag/v0.2.2",
          "title": "/releases/tag/v0.2.2",
          "count": 1,
          "uniques": 1
        },
        {
          "path": "/NYBaywatch/agrusscanner",
          "title": "Overview",
          "count": 1,
          "uniques": 1
        }
      ]
    },
    {
      "date": "2026-04-21",
      "pages": [
        {
          "path": "/NYBaywatch/AgrusScanner",
          "title": "Overview",
          "count": 4,
          "uniques": 3
        },
        {
          "path": "/NYBaywatch/AgrusScanner/issues",
          "title": "/issues",
          "count": 1,
          "uniques": 1
        },
        {
          "path": "/NYBaywatch/AgrusScanner/releases/tag/v0.2.2",
          "title": "/releases/tag/v0.2.2",
          "count": 1,
          "uniques": 1
        },
        {
          "path": "/NYBaywatch/agrusscanner",
          "title": "Overview",
          "count": 1,
          "uniques": 1
        }
      ]
    },
    {
      "date": "2026-04-22",
      "pages": [
        {
          "path": "/NYBaywatch/AgrusScanner",
          "title": "Overview",
          "count": 2,
          "uniques": 2
        },
        {
          "path": "/NYBaywatch/agrusscanner",
          "title": "Overview",
          "count": 1,
          "uniques": 1
        }
      ]
    },
    {
      "date": "2026-04-23",
      "pages": [
        {
          "path": "/NYBaywatch/AgrusScanner",
          "title": "Overview",
          "count": 2,
          "uniques": 2
        },
        {
          "path": "/NYBaywatch/agrusscanner",
          "title": "Overview",
          "count": 1,
          "uniques": 1
        }
      ]
    },
    {
      "date": "2026-04-24",
      "pages": [
        {
          "path": "/NYBaywatch/AgrusScanner",
          "title": "Overview",
          "count": 1,
          "uniques": 1
        }
      ]
    },
    {
      "date": "2026-04-25",
      "pages": [
        {
          "path": "/NYBaywatch/AgrusScanner",
          "title": "Overview",
          "count": 1,
          "uniques": 1
        }
      ]
    },
    {
      "date": "2026-04-26",
      "pages": [
        {
          "path": "/NYBaywatch/AgrusScanner",
          "title": "Overview",
          "count": 2,
          "uniques": 2
        },
        {
          "path": "/NYBaywatch/AgrusScanner/releases",
          "title": "/releases",
          "count": 2,
          "uniques": 1
        }
      ]
    }
  ]
}
